L41.v
module L41 (
    input wire [1:0] A,     // 2-bit input
    input wire EN,          // Active-low enable input
    output reg [3:0] Y      // 4-bit output
);

    always @(*) begin
        if (!EN) begin       // Check for active-low enable
            case (A)
                2'b00: Y = 4'b0001;
                2'b01: Y = 4'b0010;
                2'b10: Y = 4'b0100;
                2'b11: Y = 4'b1000;
                default: Y = 4'b0000; 
            endcase
        end else begin
            Y = 4'b0000;     // When EN is high (inactive)
        end
    end

endmodule

L41_tb.v
`include "L41.v"

`timescale 1ns / 1ns

module L41_tb;

    reg [1:0] A;
    reg EN;
    wire [3:0] Y;

    L41 uut (
        A,
        EN,
        Y
    );

    initial begin
        $dumpfile("L41_tb.vcd");
        $dumpvars(0, L41_tb);

        A = 2'b00; EN = 1;
        #10;
        A = 2'b01; EN = 1;
        #10;
        A = 2'b10; EN = 1;
        #10;
        A = 2'b11; EN = 1;
        #10;

        EN = 0;
        A = 2'b00; #10;
        A = 2'b01; #10;
        A = 2'b10; #10;
        A = 2'b11; #10;

        EN = 1;
        A = 2'b00; #10;
        A = 2'b01; #10;
        A = 2'b10; #10;
        A = 2'b11; #10;

        $display("Test Complete");
        $finish;
    end

endmodule

L41_tb.vcd
$date
	Tue Aug 20 16:37:12 2024
$end
$version
	Icarus Verilog
$end
$timescale
	1ns
$end
$scope module L41_tb $end
$var wire 4 ! Y [3:0] $end
$var reg 2 " A [1:0] $end
$var reg 1 # EN $end
$scope module uut $end
$var wire 2 $ A [1:0] $end
$var wire 1 # EN $end
$var reg 4 % Y [3:0] $end
$upscope $end
$upscope $end
$enddefinitions $end
#0
$dumpvars
b0 %
b0 $
1#
b0 "
b0 !
$end
#10
b1 "
b1 $
#20
b10 "
b10 $
#30
b11 "
b11 $
#40
b1 !
b1 %
b0 "
b0 $
0#
#50
b10 !
b10 %
b1 "
b1 $
#60
b100 !
b100 %
b10 "
b10 $
#70
b1000 !
b1000 %
b11 "
b11 $
#80
b0 !
b0 %
b0 "
b0 $
1#
#90
b1 "
b1 $
#100
b10 "
b10 $
#110
b11 "
b11 $
