L43.v
module L43 (
    input wire [3:0] A,
    output reg [1:0] Y
);

    always @(*) begin
        casex (A)
            4'b1xxx: Y = 2'b11; // Highest priority: A[3] is 1
            4'b01xx: Y = 2'b10; // Next priority: A[2] is 1
            4'b001x: Y = 2'b01; // Next priority: A[1] is 1
            4'b0001: Y = 2'b00; // Lowest priority: A[0] is 1
            default: Y = 2'b00; // Default case if all inputs are 0
        endcase
    end

endmodule

L43_tb.v
`include "L43.v"

`timescale 1ns / 1ns

module L43_tb;

    reg [3:0] A;
    wire [1:0] Y;

    // Instantiate the 4-to-2 priority encoder
    L43 uut (
        A,
        Y
    );

    initial begin
        $dumpfile("L43_tb.vcd");
        $dumpvars(0, L43_tb);

        A = 4'b0000; #10;
        A = 4'b0001; #10;
        A = 4'b0010; #10;
        A = 4'b0011; #10;
        A = 4'b0100; #10;
        A = 4'b0101; #10;
        A = 4'b0110; #10;
        A = 4'b0111; #10;
        A = 4'b1000; #10;
        A = 4'b1001; #10;
        A = 4'b1010; #10;
        A = 4'b1011; #10;
        A = 4'b1100; #10;
        A = 4'b1101; #10;
        A = 4'b1110; #10;
        A = 4'b1111; #10;

        $display("Test Complete");
        $finish;
    end

endmodule

L43_tb.vcd
$date
	Tue Aug 20 16:37:55 2024
$end
$version
	Icarus Verilog
$end
$timescale
	1ns
$end
$scope module L43_tb $end
$var wire 2 ! Y [1:0] $end
$var reg 4 " A [3:0] $end
$scope module uut $end
$var wire 4 # A [3:0] $end
$var reg 2 $ Y [1:0] $end
$upscope $end
$upscope $end
$enddefinitions $end
#0
$dumpvars
b0 $
b0 #
b0 "
b0 !
$end
#10
b1 "
b1 #
#20
b1 !
b1 $
b10 "
b10 #
#30
b11 "
b11 #
#40
b10 !
b10 $
b100 "
b100 #
#50
b101 "
b101 #
#60
b110 "
b110 #
#70
b111 "
b111 #
#80
b11 !
b11 $
b1000 "
b1000 #
#90
b1001 "
b1001 #
#100
b1010 "
b1010 #
#110
b1011 "
b1011 #
#120
b1100 "
b1100 #
#130
b1101 "
b1101 #
#140
b1110 "
b1110 #
#150
b1111 "
b1111 #
